flunt/__init__.py
flunt/constants/__init__.py
flunt/constants/messages.py
flunt/localization/__init__.py
flunt/localization/flunt_regex_patterns.py
flunt/notifications/__init__.py
flunt/notifications/notifiable.py
flunt/notifications/notification.py
flunt/notifications/py.typed
flunt/protocols/__init__.py
flunt/protocols/notifiable_protocol.py
flunt/validations/__init__.py
flunt/validations/bool_validation_contract.py
flunt/validations/brazilian_document_validation_contract.py
flunt/validations/collections_validation_contract.py
flunt/validations/commons_validation_contract.py
flunt/validations/contract.py
flunt/validations/credit_card_validation_contract.py
flunt/validations/datetime_validation_contract.py
flunt/validations/email_validation_contract.py
flunt/validations/numeric_validation_contract.py
flunt/validations/py.typed
flunt/validations/strings_validation_contract.py
flunt/validations/url_validation_contract.py
flunt-3.1.0.dist-info/METADATA
flunt-3.1.0.dist-info/WHEEL
flunt-3.1.0.dist-info/entry_points.txt
flunt-3.1.0.dist-info/licenses/LICENSE
flunt-3.1.0.dist-info/RECORD
