Metadata-Version: 2.4
Name: Flunt
Version: 3.1.0
Summary: Python implementation of Domain Notification Pattern inspired by Flunt (.NET)
Project-URL: Repository, https://github.com/fazedordecodigo/PyFlunt
Project-URL: Documentation, https://github.com/fazedordecodigo/PyFlunt
Project-URL: Homepage, https://github.com/fazedordecodigo/PyFlunt
Project-URL: Changelog, https://github.com/fazedordecodigo/PyFlunt/releases
Project-URL: Tracker, https://github.com/fazedordecodigo/PyFlunt/issues
Author-email: Emerson Delatorre <contato@delatorre.dev>
Maintainer-email: Emerson Delatorre <contato@delatorre.dev>
License-Expression: MIT
License-File: LICENSE
Keywords: class-validation,class-validator,class-validator-cpf,cnpj,cpf,datetime-validation,ddd,ddd-architecture,ddd-patterns,domain-driven-design,domain-notification,domain-notification-pattern,fluent-validation,fluentvalidation,flunt,notifiable,notification,notifications,python,python3,url-validation,validation-contracts,validation-library,validations
Classifier: Development Status :: 5 - Production/Stable
Classifier: Intended Audience :: Developers
Classifier: License :: OSI Approved :: MIT License
Classifier: Natural Language :: English
Classifier: Natural Language :: Portuguese
Classifier: Natural Language :: Portuguese (Brazilian)
Classifier: Operating System :: OS Independent
Classifier: Programming Language :: Python
Classifier: Programming Language :: Python :: 3 :: Only
Classifier: Programming Language :: Python :: 3.11
Classifier: Programming Language :: Python :: 3.12
Classifier: Programming Language :: Python :: 3.13
Classifier: Programming Language :: Python :: 3.14
Classifier: Topic :: Office/Business
Classifier: Topic :: Software Development
Classifier: Topic :: Software Development :: Internationalization
Classifier: Topic :: Software Development :: Libraries :: Python Modules
Classifier: Topic :: Utilities
Classifier: Typing :: Typed
Requires-Python: >=3.11
